pycompass/__init__.py
pycompass/aggregate.py
pycompass/annotation.py
pycompass/biological_feature.py
pycompass/compendium.py
pycompass/connect.py
pycompass/experiment.py
pycompass/module.py
pycompass/ontology.py
pycompass/ontology_node.py
pycompass/platform.py
pycompass/plot.py
pycompass/query.py
pycompass/raw_data.py
pycompass/sample.py
pycompass/sample_set.py
pycompass/sparql.py
pycompass/test_compendium.py
pycompass/utils.py
pyCOMPASS-0.8.4.dist-info/LICENSE
pyCOMPASS-0.8.4.dist-info/METADATA
pyCOMPASS-0.8.4.dist-info/WHEEL
pyCOMPASS-0.8.4.dist-info/top_level.txt
pyCOMPASS-0.8.4.dist-info/RECORD
