Metadata-Version: 2.1
Name: pyCOMPASS
Version: 0.8.4
Summary: A Python interface to COMPASS, the gene expression compendia GraphQL endpoint
Home-page: UNKNOWN
Author: Marco Moretto
Author-email: marco.moretto@fmach.it
License: UNKNOWN
Platform: UNKNOWN
Classifier: Programming Language :: Python :: 3
Classifier: License :: OSI Approved :: GNU General Public License v3 (GPLv3)
Classifier: Operating System :: OS Independent
Requires-Dist: requests
Requires-Dist: numpy
